LICENSE
README.md
cloudflarestatus/__init__.py
cloudflarestatus/cloudflarestatus.py
cloudflarestatus-0.0.2.dist-info/METADATA
cloudflarestatus-0.0.2.dist-info/WHEEL
cloudflarestatus-0.0.2.dist-info/entry_points.txt
cloudflarestatus-0.0.2.dist-info/licenses/LICENSE
cloudflarestatus-0.0.2.dist-info/RECORD
