Metadata-Version: 2.1
Name: cloudflarestatus
Version: 0.0.2
Summary: Parse Cloudflare System Status from https://www.cloudflarestatus.com
Project-URL: Homepage, https://github.com/ayeowch/cloudflarestatus
Project-URL: Bug Tracker, https://github.com/ayeowch/cloudflarestatus/issues
Author-email: Addy Yeow <ayeowch@gmail.com>
License-File: LICENSE
Classifier: Intended Audience :: Developers
Classifier: License :: OSI Approved :: MIT License
Classifier: Operating System :: OS Independent
Classifier: Programming Language :: Python
Classifier: Programming Language :: Python :: 3
Classifier: Topic :: System :: Monitoring
Classifier: Topic :: System :: Networking :: Monitoring
Classifier: Topic :: System :: Systems Administration
Requires-Python: >=3.11
Requires-Dist: beautifulsoup4
Requires-Dist: requests
